{
	"configurations" : 
	[
		{
			"directories" : 
			[
				{
					"build" : ".",
					"hasInstallRule" : true,
					"jsonFile" : "directory-.-Release-fcecf9baaedae90976c0.json",
					"minimumCMakeVersion" : 
					{
						"string" : "3.20"
					},
					"projectIndex" : 0,
					"source" : ".",
					"targetIndexes" : 
					[
						0,
						1,
						2
					]
				}
			],
			"name" : "Release",
			"projects" : 
			[
				{
					"directoryIndexes" : 
					[
						0
					],
					"name" : "serial",
					"targetIndexes" : 
					[
						0,
						1,
						2
					]
				}
			],
			"targets" : 
			[
				{
					"directoryIndex" : 0,
					"id" : "serial::@6890427a1f51a3e7e1df",
					"jsonFile" : "target-serial-Release-ed54b98bc42b7c9c24fe.json",
					"name" : "serial",
					"projectIndex" : 0
				},
				{
					"directoryIndex" : 0,
					"id" : "serial_uninstall::@6890427a1f51a3e7e1df",
					"jsonFile" : "target-serial_uninstall-Release-27d9dfbe184fd0809bd0.json",
					"name" : "serial_uninstall",
					"projectIndex" : 0
				},
				{
					"directoryIndex" : 0,
					"id" : "uninstall::@6890427a1f51a3e7e1df",
					"jsonFile" : "target-uninstall-Release-06619db96b6a6ed0a917.json",
					"name" : "uninstall",
					"projectIndex" : 0
				}
			]
		}
	],
	"kind" : "codemodel",
	"paths" : 
	{
		"build" : "/home/luka/ws_moveit/build/serial",
		"source" : "/home/luka/ws_moveit/src/serial"
	},
	"version" : 
	{
		"major" : 2,
		"minor" : 6
	}
}
